[
  {
    "name": "[SubsPlease] Sayonara Watashi no Cramer - 05 (1080p) [993B89C5].zh-Hant.srt",
    "path": "Offline/Anime_Offline/再见了，我的克拉默",
    "url": "https://i0.hdslb.com/bfs/subtitle/646ff2c864cfda7018a2864e5a38a0c5742f3748.json",
    "delay": 0
  },
  {
    "name": "[SubsPlease] Dragon, Ie wo Kau. - 05 (1080p) [11907FF3].zh-Hans.srt",
    "path": "Offline/Anime_Offline/龙先生，想要买个家。",
    "url": "https://i0.hdslb.com/bfs/subtitle/5a277fd535fb0d626477e16542ce4ed2da3396ff.json",
    "delay": 7.15
  }
]